{
  "ItemID": "18073",
  "FullTitle": "Proceedings of the Academy of Natural Sciences of Philadelphia.",
  "VolumeInfo": "v. 46 (1894)",
  "articles": [
    {
      "reference_id": "59668",
      "genre": "article",
      "title": "List of Port Jackson chitons collected by Dr J.C. Cox, with a revision of Australian Acanthochitidae",
      "secondary_title": "Proceedings of the Academy of Natural Sciences of Philadelphia",
      "volume": "46",
      "spage": "69",
      "epage": "88",
      "year": "1894",
      "date": "1894-00-00",
      "issn": "0097-3157",
      "PageID": "1867395",
      "created": "2010-11-22 15:07:00",
      "updated": "2011-06-21 14:00:53",
      "TitlePageID": "0",
      "authors": [
        {
          "id": "42094",
          "lastname": "Pilsbry",
          "forename": "H A"
        }
      ],
      "bhl_pages": [
        1867395,
        1867336,
        1867337,
        1867321,
        1867322,
        1867323,
        1867324,
        1867325,
        1867326,
        1867327,
        1867328,
        1867329,
        1867330,
        1867331,
        1867332,
        1867333,
        1867334,
        1867335,
        1867338,
        1867339
      ]
    },
    {
      "reference_id": "60084",
      "genre": "article",
      "title": "Tanais robustus, a new species of Anisopoda",
      "secondary_title": "Proceedings of the Academy of Natural Sciences of Philadelphia",
      "volume": "46",
      "spage": "90",
      "epage": "94",
      "year": "1894",
      "date": "1894-00-00",
      "issn": "0097-3157",
      "PageID": "1867341",
      "created": "2010-11-22 18:30:08",
      "updated": "2011-06-21 14:00:53",
      "TitlePageID": "0",
      "authors": [
        {
          "id": "42758",
          "lastname": "Moore",
          "forename": "H F"
        }
      ],
      "bhl_pages": [
        1867341,
        1867342,
        1867343,
        1867344,
        1867345
      ]
    },
    {
      "reference_id": "49053",
      "genre": "article",
      "title": "Third addition to a knowledge of the batrachia and reptilia of Costa Rica",
      "secondary_title": "Proc. Acad. Nat. Sci. Philadelphia",
      "volume": "1894",
      "spage": "194",
      "epage": "206",
      "year": "1894",
      "date": "1894-00-00",
      "issn": "0097-3157",
      "PageID": "1867514",
      "created": "2010-03-21 11:06:28",
      "updated": "2011-10-03 09:30:57",
      "TitlePageID": "0",
      "authors": [
        {
          "id": "8524",
          "lastname": "Cope",
          "forename": "E D"
        }
      ],
      "bhl_pages": [
        1867514,
        1867515,
        1867516,
        1867517,
        1867518,
        1867519,
        1867520,
        1867521,
        1867522,
        1867523,
        1867524,
        1867525,
        1867526
      ]
    },
    {
      "reference_id": "53321",
      "genre": "article",
      "title": "List of the Diptera of Jamaica with descriptions of new species",
      "secondary_title": "Proceedings of the Academy of Natural Sciences of Philadelphia",
      "volume": "1894",
      "spage": "271",
      "epage": "281",
      "year": "1894",
      "date": "1894-00-00",
      "issn": "0097-3157",
      "PageID": "1867591",
      "created": "2010-10-26 20:13:40",
      "updated": "2011-06-21 14:00:53",
      "TitlePageID": "0",
      "authors": [
        {
          "id": "10112",
          "lastname": "Johnson",
          "forename": "C W"
        }
      ],
      "bhl_pages": [
        1867591,
        1867592,
        1867593,
        1867594,
        1867595,
        1867596,
        1867597,
        1867598,
        1867599,
        1867600,
        1867601
      ]
    }
  ]
}