{
  "ItemID": "21086",
  "FullTitle": "Siphonaptera collected during the 1965 Street Expedition to Afghanistan  [by] Robert E. Lewis.",
  "VolumeInfo": "v.64(1973)",
  "articles": [
    {
      "reference_id": "95656",
      "genre": "article",
      "title": "Siphonaptera collected during the 1965 Street Expedition to Afghanistan",
      "secondary_title": "Fieldiana Zoology",
      "volume": "64",
      "spage": "1",
      "epage": "161",
      "year": "1973",
      "date": "1973-00-00",
      "issn": "0015-0754",
      "PageID": "2784545",
      "created": "2011-10-07 00:22:48",
      "updated": "2011-10-07 08:15:10",
      "TitlePageID": "0",
      "authors": [
        {
          "id": "22954",
          "lastname": "Lewis",
          "forename": "Robert E"
        }
      ],
      "bhl_pages": [
        2784545,
        2784546,
        2784547,
        2784548,
        2784549,
        2784550,
        2784551,
        2784552,
        2784553,
        2784554,
        2784555,
        2784556,
        2784557,
        2784558,
        2784559,
        2784560,
        2784561,
        2784562,
        2784563,
        2784564,
        2784565,
        2784566,
        2784567,
        2784568,
        2784569,
        2784570,
        2784571,
        2784572,
        2784573,
        2784574,
        2784575,
        2784576,
        2784577,
        2784578,
        2784579,
        2784580,
        2784581,
        2784582,
        2784583,
        2784584,
        2784585,
        2784586,
        2784587,
        2784588,
        2784589,
        2784590,
        2784591,
        2784592,
        2784593,
        2784594,
        2784595,
        2784596,
        2784597,
        2784598,
        2784599,
        2784600,
        2784601,
        2784602,
        2784603,
        2784604,
        2784605,
        2784606,
        2784607,
        2784608,
        2784609,
        2784610,
        2784611,
        2784612,
        2784613,
        2784614,
        2784615,
        2784616,
        2784617,
        2784618,
        2784619,
        2784620,
        2784621,
        2784622,
        2784623,
        2784624,
        2784625,
        2784626,
        2784627,
        2784628,
        2784629,
        2784630,
        2784631,
        2784632,
        2784633,
        2784634,
        2784635,
        2784636,
        2784637,
        2784638,
        2784639,
        2784640,
        2784641,
        2784642,
        2784643,
        2784644,
        2784645,
        2784646,
        2784647,
        2784648,
        2784649,
        2784650,
        2784651,
        2784652,
        2784653,
        2784654,
        2784655,
        2784656,
        2784657,
        2784658,
        2784659,
        2784660,
        2784661,
        2784662,
        2784663,
        2784664,
        2784665,
        2784666,
        2784667,
        2784668,
        2784669,
        2784670,
        2784671,
        2784672,
        2784673,
        2784674,
        2784675,
        2784676,
        2784677,
        2784678,
        2784679,
        2784680,
        2784681,
        2784682,
        2784683,
        2784684,
        2784685,
        2784686,
        2784687,
        2784688,
        2784689,
        2784690,
        2784691,
        2784692,
        2784693,
        2784694,
        2784695,
        2784696,
        2784697,
        2784698,
        2784699,
        2784700,
        2784701,
        2784702,
        2784703,
        2784704,
        2784705
      ]
    }
  ]
}