{
  "ItemID": "35769",
  "FullTitle": "The Great Basin naturalist.",
  "VolumeInfo": "v.43 (1983)",
  "articles": [
    {
      "reference_id": "70783",
      "genre": "article",
      "title": "A review of the genus Soliperla (Plecoptera: Peltoperlidae)",
      "secondary_title": "Great Basin Naturalist",
      "volume": "43",
      "spage": "30",
      "epage": "44",
      "year": "1983",
      "date": "1983-00-00",
      "issn": "0017-3614",
      "PageID": "8883769",
      "created": "2011-06-03 07:11:36",
      "updated": "2011-06-21 14:00:53",
      "TitlePageID": "0",
      "authors": [
        {
          "id": "46175",
          "lastname": "",
          "forename": "Stark"
        }
      ],
      "bhl_pages": [
        8883769,
        8883770,
        8883771,
        8883772,
        8883773,
        8883774,
        8883775,
        8883776,
        8883777,
        8883778,
        8883779,
        8883780,
        8883781,
        8883805,
        8883806
      ]
    },
    {
      "reference_id": "85289",
      "genre": "article",
      "title": "A revision of the genus Microrhopala (Coleoptera: Chrysomelidae) in America north of Mexico",
      "secondary_title": "Great Basin Naturalist",
      "volume": "43",
      "spage": "597",
      "epage": "618",
      "year": "1983",
      "date": "1983-00-00",
      "issn": "0017-3614",
      "PageID": "8884373",
      "created": "2011-08-12 09:18:16",
      "updated": "2011-08-12 09:18:16",
      "TitlePageID": "0",
      "authors": [
        
      ],
      "bhl_pages": [
        8884373,
        8884374,
        8884375,
        8884376,
        8884377,
        8884378,
        8884379,
        8884380,
        8884381,
        8884382,
        8884383,
        8884384,
        8884385,
        8884386,
        8884387,
        8884388,
        8884389,
        8884390,
        8884391,
        8884392,
        8884393,
        8884394
      ]
    },
    {
      "reference_id": "99483",
      "genre": "article",
      "title": "New synonymy and new species of American bark beetles (Coleoptera: Scolytidae), part 9",
      "secondary_title": "Great Basin Naturalist",
      "volume": "43",
      "spage": "647",
      "epage": "659",
      "year": "1983",
      "date": "1983-00-00",
      "issn": "0017-3614",
      "PageID": "8884423",
      "created": "2011-12-15 17:05:26",
      "updated": "2011-12-15 17:05:26",
      "TitlePageID": "0",
      "authors": [
        
      ],
      "bhl_pages": [
        8884423,
        8884424,
        8884425,
        8884426,
        8884427,
        8884428,
        8884429,
        8884430,
        8884431,
        8884432,
        8884433,
        8884434,
        8884435
      ]
    },
    {
      "reference_id": "85321",
      "genre": "article",
      "title": "New leafhopper species of Coelidia with a revised key and notes on homonymy and distribution (Homoptera: Cicadellidae, Coelidiinae)",
      "secondary_title": "Great Basin Naturalist",
      "volume": "43",
      "spage": "669",
      "epage": "674",
      "year": "1983",
      "date": "1983-00-00",
      "issn": "0017-3614",
      "PageID": "8884445",
      "created": "2011-08-12 09:20:57",
      "updated": "2011-08-12 09:20:57",
      "TitlePageID": "0",
      "authors": [
        
      ],
      "bhl_pages": [
        8884445,
        8884446,
        8884447,
        8884448,
        8884449,
        8884450
      ]
    }
  ]
}