{
  "ItemID": "39854",
  "FullTitle": "Bullettino della Societ\u00e0 entomologica italiana.",
  "VolumeInfo": "v. 15 1883",
  "articles": [
    {
      "reference_id": "61497",
      "genre": "article",
      "title": "Alcune formiche della Nuova Caledonia",
      "secondary_title": "Bollettino della Societ\u00e0 Entomologica Italiana",
      "volume": "15",
      "spage": "145",
      "epage": "151",
      "year": "1883",
      "date": "1883-00-00",
      "issn": "0373-3491",
      "PageID": "10440759",
      "created": "2011-01-10 21:11:59",
      "updated": "2011-06-21 14:00:53",
      "TitlePageID": "0",
      "authors": [
        {
          "id": "18307",
          "lastname": "Emery",
          "forename": "C"
        }
      ],
      "bhl_pages": [
        10440759,
        10440760,
        10440761,
        10440762,
        10440763,
        10440764,
        10440765
      ]
    },
    {
      "reference_id": "61573",
      "genre": "article",
      "title": "Escursione in Sicilia. Acarofauna Sicula",
      "secondary_title": "Bollettino della Societ\u00e0 Entomologica Italiana",
      "volume": "15",
      "spage": "212",
      "epage": "220",
      "year": "1883",
      "date": "1883-00-00",
      "issn": "0373-3491",
      "PageID": "10440826",
      "created": "2011-01-10 22:07:03",
      "updated": "2011-06-21 14:00:53",
      "TitlePageID": "0",
      "authors": [
        {
          "id": "42106",
          "lastname": "Berlese",
          "forename": "A"
        }
      ],
      "bhl_pages": [
        10440826,
        10440827,
        10440828,
        10440829,
        10440830,
        10440831,
        10440832,
        10440833,
        10440834
      ]
    },
    {
      "reference_id": "61534",
      "genre": "article",
      "title": "Fauna degliaidi della provincia di Reggio di Calabria",
      "secondary_title": "Bollettino della Societ\u00e0 Entomologica Italiana",
      "volume": "15",
      "spage": "227",
      "epage": "240",
      "year": "1883",
      "date": "1883-00-00",
      "issn": "0373-3491",
      "PageID": "10440841",
      "created": "2011-01-10 21:41:57",
      "updated": "2011-06-21 14:00:53",
      "TitlePageID": "0",
      "authors": [
        {
          "id": "43060",
          "lastname": "Macchiati",
          "forename": "L"
        }
      ],
      "bhl_pages": [
        10440841,
        10440842,
        10440843,
        10440844,
        10440845,
        10440846,
        10440847,
        10440848,
        10440849,
        10440850,
        10440851,
        10440852,
        10440853,
        10440854
      ]
    },
    {
      "reference_id": "72946",
      "genre": "article",
      "title": "Roccolte imenotterologiche nell'Africa orientale",
      "secondary_title": "Bollettino della Societa Entomologica Italiana",
      "volume": "15",
      "spage": "241",
      "epage": "253",
      "year": "1884",
      "date": "1884-00-00",
      "issn": "0373-3491",
      "PageID": "10440855",
      "created": "2011-06-04 04:43:52",
      "updated": "2011-06-21 14:00:53",
      "TitlePageID": "0",
      "authors": [
        {
          "id": "47095",
          "lastname": "Magretti",
          "forename": "P"
        }
      ],
      "bhl_pages": [
        10440855,
        10440856,
        10440857,
        10440858,
        10440859,
        10440860,
        10440861,
        10440862,
        10440863,
        10440864,
        10440865,
        10440866,
        10440867
      ]
    },
    {
      "reference_id": "71196",
      "genre": "article",
      "title": "Diagnosi di nuovi Artropodi trovati in Sardegna (1)",
      "secondary_title": "Bollettino Societa Entomologia Italiana",
      "volume": "15",
      "spage": "332",
      "epage": "341",
      "year": "1883",
      "date": "1883-00-00",
      "oclc": "1765746",
      "PageID": "10440948",
      "created": "2011-06-03 18:06:48",
      "updated": "2011-06-21 14:00:53",
      "TitlePageID": "0",
      "authors": [
        {
          "id": "42956",
          "lastname": "Costa",
          "forename": "A"
        }
      ],
      "bhl_pages": [
        10440948,
        10440949,
        10440950,
        10440951,
        10440952,
        10440953,
        10440954,
        10440955,
        10440956,
        10440957
      ]
    }
  ]
}