{
  "ItemID": "44211",
  "FullTitle": "Transactions of the Entomological Society of London.",
  "VolumeInfo": "1898",
  "articles": [
    {
      "reference_id": "50866",
      "genre": "article",
      "title": "II. Some Results of Recent Experiments in Hybridising Tephrosia bistortata and Tephrosia crepuscularia. By James William Tutt, F.E.S",
      "secondary_title": "Transactions of The Royal Entomological Society of London",
      "volume": "46",
      "spage": "17",
      "epage": "42",
      "year": "1898",
      "date": "1898-00-00",
      "issn": "0035-8894",
      "doi": "10.1111\/j.1365-2311.1898.tb02359.x",
      "PageID": "12113650",
      "created": "2010-06-23 17:12:56",
      "updated": "2012-05-25 09:14:10",
      "TitlePageID": "0",
      "authors": [
        {
          "id": "35972",
          "lastname": "",
          "forename": ""
        }
      ],
      "bhl_pages": [
        12113650,
        12113651,
        12113652,
        12113653,
        12113654,
        12113655,
        12113656,
        12113657,
        12113658,
        12113659,
        12113660,
        12113661,
        12113662,
        12113663,
        12113664,
        12113665,
        12113666,
        12113667,
        12113668,
        12113669,
        12113670,
        12113671,
        12113672,
        12113673,
        12113674,
        12113675
      ]
    },
    {
      "reference_id": "50867",
      "genre": "article",
      "title": "III. A List of Rumanian Orthopteru, with Descriptions of Three New Species. By Malcolm Burr, F.Z.S",
      "secondary_title": "Transactions of The Royal Entomological Society of London",
      "volume": "46",
      "spage": "43",
      "epage": "53",
      "year": "1898",
      "date": "1898-00-00",
      "issn": "0035-8894",
      "doi": "10.1111\/j.1365-2311.1898.tb02360.x",
      "PageID": "12113676",
      "created": "2010-06-23 17:12:59",
      "updated": "2012-05-25 09:14:10",
      "TitlePageID": "0",
      "authors": [
        {
          "id": "35972",
          "lastname": "",
          "forename": ""
        }
      ],
      "bhl_pages": [
        12113676,
        12113677,
        12113678,
        12113679,
        12113680,
        12113681,
        12113682,
        12113683,
        12113684,
        12113685,
        12113686
      ]
    },
    {
      "reference_id": "50868",
      "genre": "article",
      "title": "IV. Notes on American and other Tingitid\u00e6, with Descriptions of two new Genera and four Species. By George Charles Champion, F.Z.S",
      "secondary_title": "Transactions of The Royal Entomological Society of London",
      "volume": "46",
      "spage": "55",
      "epage": "64",
      "year": "1898",
      "date": "1898-00-00",
      "issn": "0035-8894",
      "doi": "10.1111\/j.1365-2311.1898.tb02361.x",
      "PageID": "12113688",
      "created": "2010-06-23 17:13:02",
      "updated": "2012-05-25 09:14:10",
      "TitlePageID": "0",
      "authors": [
        {
          "id": "35972",
          "lastname": "",
          "forename": ""
        }
      ],
      "bhl_pages": [
        12113688,
        12113689,
        12113690,
        12113691,
        12113692,
        12113693,
        12113694,
        12113695,
        12113696,
        12113697
      ]
    },
    {
      "reference_id": "50869",
      "genre": "article",
      "title": "V. A List of the CicindelidaB, Carabid\u00e6and Staphy-linid\u00e6collected by Mr. J. J. Walker, R.N., F.L.S., in the region of the Straits of Gibraltar. By George Charles Champion, F.Z.S",
      "secondary_title": "Transactions of The Royal Entomological Society of London",
      "volume": "46",
      "spage": "65",
      "epage": "103",
      "year": "1898",
      "date": "1898-00-00",
      "issn": "0035-8894",
      "doi": "10.1111\/j.1365-2311.1898.tb02362.x",
      "PageID": "12113698",
      "created": "2010-06-23 17:13:05",
      "updated": "2012-05-25 09:14:10",
      "TitlePageID": "0",
      "authors": [
        {
          "id": "35972",
          "lastname": "",
          "forename": ""
        }
      ],
      "bhl_pages": [
        12113698,
        12113699,
        12113700,
        12113701,
        12113702,
        12113703,
        12113704,
        12113705,
        12113706,
        12113707,
        12113708,
        12113709,
        12113710,
        12113711,
        12113712,
        12113713,
        12113714,
        12113715,
        12113716,
        12113717,
        12113718,
        12113719,
        12113720,
        12113721,
        12113722,
        12113723,
        12113724,
        12113725,
        12113726,
        12113727,
        12113728,
        12113729,
        12113730,
        12113731,
        12113732,
        12113733,
        12113734,
        12113735,
        12113736
      ]
    },
    {
      "reference_id": "50870",
      "genre": "article",
      "title": "VI. Descriptions of New Species of American Rhopalocera. By F. Du Cane Godman, F.R.S., and Osbert Salvin, M.A., F.R.S",
      "secondary_title": "Transactions of The Royal Entomological Society of London",
      "volume": "46",
      "spage": "105",
      "epage": "112",
      "year": "1898",
      "date": "1898-00-00",
      "issn": "0035-8894",
      "doi": "10.1111\/j.1365-2311.1898.tb02363.x",
      "PageID": "12113738",
      "created": "2010-06-23 17:13:08",
      "updated": "2012-05-25 09:14:10",
      "TitlePageID": "0",
      "authors": [
        {
          "id": "35972",
          "lastname": "",
          "forename": ""
        }
      ],
      "bhl_pages": [
        12113738,
        12113739,
        12113740,
        12113741,
        12113742,
        12113743,
        12113744,
        12113745
      ]
    },
    {
      "reference_id": "50871",
      "genre": "article",
      "title": "VII. On some Phytophagous Coleoptera (Eumolpid\u00e6) from the Islands of Mauritius and R\u00e9union. By Martin Jacoby, F.E.S",
      "secondary_title": "Transactions of The Royal Entomological Society of London",
      "volume": "46",
      "spage": "113",
      "epage": "120",
      "year": "1898",
      "date": "1898-00-00",
      "issn": "0035-8894",
      "doi": "10.1111\/j.1365-2311.1898.tb02364.x",
      "PageID": "12113746",
      "created": "2010-06-23 17:13:16",
      "updated": "2012-05-25 09:14:10",
      "TitlePageID": "0",
      "authors": [
        {
          "id": "35972",
          "lastname": "",
          "forename": ""
        }
      ],
      "bhl_pages": [
        12113746,
        12113747,
        12113748,
        12113749,
        12113750,
        12113751,
        12113752,
        12113753
      ]
    },
    {
      "reference_id": "50861",
      "genre": "article",
      "title": "VIII. On the Frenulum of the Lepidoptcra. By George Charles Griffiths, F.Z.S., F.E.S",
      "secondary_title": "Transactions of The Royal Entomological Society of London",
      "volume": "46",
      "spage": "121",
      "epage": "132",
      "year": "1898",
      "date": "1898-00-00",
      "issn": "0035-8894",
      "doi": "10.1111\/j.1365-2311.1898.tb02369.x",
      "PageID": "12113754",
      "created": "2010-06-23 17:12:39",
      "updated": "2012-05-25 09:14:10",
      "TitlePageID": "0",
      "authors": [
        {
          "id": "35972",
          "lastname": "",
          "forename": ""
        }
      ],
      "bhl_pages": [
        12113754,
        12113755,
        12113756,
        12113757,
        12113758,
        12113759,
        12113760,
        12113761,
        12113762,
        12113763,
        12113764,
        12113765
      ]
    },
    {
      "reference_id": "50862",
      "genre": "article",
      "title": "IX. The Larva of Pelophila. By the Rev. William Frederick Johnson, M.A., F.E.S., and George H. Carpenter, B. Sc, F.E.S",
      "secondary_title": "Transactions of The Royal Entomological Society of London",
      "volume": "46",
      "spage": "133",
      "epage": "140",
      "year": "1898",
      "date": "1898-00-00",
      "issn": "0035-8894",
      "doi": "10.1111\/j.1365-2311.1898.tb02370.x",
      "PageID": "12113766",
      "created": "2010-06-23 17:12:41",
      "updated": "2012-05-25 09:14:10",
      "TitlePageID": "0",
      "authors": [
        {
          "id": "35972",
          "lastname": "",
          "forename": ""
        }
      ],
      "bhl_pages": [
        12113766,
        12113767,
        12113768,
        12113769,
        12113770,
        12113771,
        12113772,
        12113773
      ]
    },
    {
      "reference_id": "50863",
      "genre": "article",
      "title": "X. Some Remarks on Heterogyna penella. By Thomas Algernon Chapman, M.D., F.E.S",
      "secondary_title": "Transactions of The Royal Entomological Society of London",
      "volume": "46",
      "spage": "141",
      "epage": "150",
      "year": "1898",
      "date": "1898-00-00",
      "issn": "0035-8894",
      "doi": "10.1111\/j.1365-2311.1898.tb02371.x",
      "PageID": "12113774",
      "created": "2010-06-23 17:12:43",
      "updated": "2012-05-25 09:14:10",
      "TitlePageID": "0",
      "authors": [
        {
          "id": "35972",
          "lastname": "",
          "forename": ""
        }
      ],
      "bhl_pages": [
        12113774,
        12113775,
        12113776,
        12113777,
        12113778,
        12113779,
        12113780,
        12113781,
        12113782,
        12113783
      ]
    },
    {
      "reference_id": "50864",
      "genre": "article",
      "title": "XI. Neuroptera-Planipennia collected in Algeria by the Rev. A. E. Eaton. By Robert McLachlan, F.R.S., &c",
      "secondary_title": "Transactions of The Royal Entomological Society of London",
      "volume": "46",
      "spage": "151",
      "epage": "168",
      "year": "1898",
      "date": "1898-00-00",
      "issn": "0035-8894",
      "doi": "10.1111\/j.1365-2311.1898.tb02372.x",
      "PageID": "12113784",
      "created": "2010-06-23 17:12:46",
      "updated": "2012-05-25 09:14:10",
      "TitlePageID": "0",
      "authors": [
        {
          "id": "35972",
          "lastname": "",
          "forename": ""
        }
      ],
      "bhl_pages": [
        12113784,
        12113785,
        12113786,
        12113787,
        12113788,
        12113789,
        12113790,
        12113791,
        12113792,
        12113793,
        12113794,
        12113795,
        12113796,
        12113797,
        12113798,
        12113799,
        12113800,
        12113801
      ]
    },
    {
      "reference_id": "50865",
      "genre": "article",
      "title": "XII. A Revision of the Genus Erebia. By Henry John Elwes, F.R.S., F.L.S., &c",
      "secondary_title": "Transactions of The Royal Entomological Society of London",
      "volume": "46",
      "spage": "169",
      "epage": "207",
      "year": "1898",
      "date": "1898-00-00",
      "issn": "0035-8894",
      "doi": "10.1111\/j.1365-2311.1898.tb02373.x",
      "PageID": "12113802",
      "created": "2010-06-23 17:12:50",
      "updated": "2012-05-25 09:14:10",
      "TitlePageID": "0",
      "authors": [
        {
          "id": "35972",
          "lastname": "",
          "forename": ""
        }
      ],
      "bhl_pages": [
        12113802,
        12113803,
        12113804,
        12113805,
        12113806,
        12113807,
        12113808,
        12113809,
        12113810,
        12113811,
        12113812,
        12113813,
        12113814,
        12113815,
        12113816,
        12113817,
        12113818,
        12113819,
        12113820,
        12113821,
        12113822,
        12113823,
        12113824,
        12113825,
        12113826,
        12113827,
        12113828,
        12113829,
        12113830,
        12113831,
        12113832,
        12113833,
        12113834,
        12113835,
        12113836,
        12113837,
        12113838,
        12113839,
        12113840
      ]
    },
    {
      "reference_id": "50857",
      "genre": "article",
      "title": "XIII. A Beview of the Genus Erebia, based on an Examination of the Male Appendages. By Thomas Algernon Chapman, M.D., F.E.S",
      "secondary_title": "Transactions of The Royal Entomological Society of London",
      "volume": "46",
      "spage": "209",
      "epage": "235",
      "year": "1898",
      "date": "1898-00-00",
      "issn": "0035-8894",
      "doi": "10.1111\/j.1365-2311.1898.tb02374.x",
      "PageID": "12113842",
      "created": "2010-06-23 17:12:22",
      "updated": "2012-05-25 09:14:10",
      "TitlePageID": "0",
      "authors": [
        {
          "id": "35972",
          "lastname": "",
          "forename": ""
        }
      ],
      "bhl_pages": [
        12113842,
        12113843,
        12113844,
        12113845,
        12113846,
        12113847,
        12113848,
        12113849,
        12113850,
        12113851,
        12113852,
        12113853,
        12113854,
        12113855,
        12113856,
        12113857,
        12113858,
        12113859,
        12113860,
        12113861,
        12113862,
        12113863,
        12113864,
        12113865,
        12113866,
        12113867,
        12113868
      ]
    },
    {
      "reference_id": "50858",
      "genre": "article",
      "title": "EXPLANATION OF PLATES V-XVI",
      "secondary_title": "Transactions of The Royal Entomological Society of London",
      "volume": "46",
      "spage": "235",
      "epage": "239",
      "year": "1898",
      "date": "1898-00-00",
      "issn": "0035-8894",
      "doi": "10.1111\/j.1365-2311.1898.tb02375.x",
      "PageID": "12113868",
      "created": "2010-06-23 17:12:24",
      "updated": "2012-05-25 09:14:10",
      "TitlePageID": "0",
      "authors": [
        {
          "id": "35972",
          "lastname": "",
          "forename": ""
        }
      ],
      "bhl_pages": [
        12113868,
        12113869,
        12113870,
        12113871,
        12113872
      ]
    },
    {
      "reference_id": "50859",
      "genre": "article",
      "title": "XIV. The Moths of the Lesser Antilles. By Sir George F. Hampson, Bart., B.A",
      "secondary_title": "Transactions of The Royal Entomological Society of London",
      "volume": "46",
      "spage": "241",
      "epage": "260",
      "year": "1898",
      "date": "1898-00-00",
      "issn": "0035-8894",
      "doi": "10.1111\/j.1365-2311.1898.tb02376.x",
      "PageID": "12113874",
      "created": "2010-06-23 17:12:26",
      "updated": "2012-05-25 09:14:10",
      "TitlePageID": "0",
      "authors": [
        {
          "id": "35972",
          "lastname": "",
          "forename": ""
        }
      ],
      "bhl_pages": [
        12113874,
        12113875,
        12113876,
        12113877,
        12113878,
        12113879,
        12113880,
        12113881,
        12113882,
        12113883,
        12113884,
        12113885,
        12113886,
        12113887,
        12113888,
        12113889,
        12113890,
        12113891,
        12113892,
        12113893
      ]
    },
    {
      "reference_id": "50860",
      "genre": "article",
      "title": "XV. Lepidoptera Heterocera from Northern China, Japan, and Corea. By John Henry Leech, B.A., F.L.S., F.Z.S., &c",
      "secondary_title": "Transactions of The Royal Entomological Society of London",
      "volume": "46",
      "spage": "261",
      "epage": "379",
      "year": "1898",
      "date": "1898-00-00",
      "issn": "0035-8894",
      "doi": "10.1111\/j.1365-2311.1898.tb02377.x",
      "PageID": "12113894",
      "created": "2010-06-23 17:12:28",
      "updated": "2012-05-25 09:14:10",
      "TitlePageID": "0",
      "authors": [
        {
          "id": "35972",
          "lastname": "",
          "forename": ""
        }
      ],
      "bhl_pages": [
        12113894,
        12113895,
        12113896,
        12113897,
        12113898,
        12113899,
        12113900,
        12113901,
        12113902,
        12113903,
        12113904,
        12113905,
        12113906,
        12113907,
        12113908,
        12113909,
        12113910,
        12113911,
        12113912,
        12113913,
        12113914,
        12113915,
        12113916,
        12113917,
        12113918,
        12113919,
        12113920,
        12113921,
        12113922,
        12113923,
        12113924,
        12113925,
        12113926,
        12113927,
        12113928,
        12113929,
        12113930,
        12113931,
        12113932,
        12113933,
        12113934,
        12113935,
        12113936,
        12113937,
        12113938,
        12113939,
        12113940,
        12113941,
        12113942,
        12113943,
        12113944,
        12113945,
        12113946,
        12113947,
        12113948,
        12113949,
        12113950,
        12113951,
        12113952,
        12113953,
        12113954,
        12113955,
        12113956,
        12113957,
        12113958,
        12113959,
        12113960,
        12113961,
        12113962,
        12113963,
        12113964,
        12113965,
        12113966,
        12113967,
        12113968,
        12113969,
        12113970,
        12113971,
        12113972,
        12113973,
        12113974,
        12113975,
        12113976,
        12113977,
        12113978,
        12113979,
        12113980,
        12113981,
        12113982,
        12113983,
        12113984,
        12113985,
        12113986,
        12113987,
        12113988,
        12113989,
        12113990,
        12113991,
        12113992,
        12113993,
        12113994,
        12113995,
        12113996,
        12113997,
        12113998,
        12113999,
        12114000,
        12114001,
        12114002,
        12114003,
        12114004,
        12114005,
        12114006,
        12114007,
        12114008,
        12114009,
        12114010,
        12114011,
        12114012
      ]
    },
    {
      "reference_id": "50850",
      "genre": "article",
      "title": "XVI. Further notes on Dyscritina, Westw. By E. Ernest Green, F.E.S. With an Appendix on the species of Dyscritina reared by Mr. Green. By Malcolm Burr, F.Z.S., F.E.S",
      "secondary_title": "Transactions of The Royal Entomological Society of London",
      "volume": "46",
      "spage": "381",
      "epage": "390",
      "year": "1898",
      "date": "1898-00-00",
      "issn": "0035-8894",
      "doi": "10.1111\/j.1365-2311.1898.tb03294.x",
      "PageID": "12114014",
      "created": "2010-06-23 17:12:05",
      "updated": "2012-05-25 09:14:10",
      "TitlePageID": "0",
      "authors": [
        {
          "id": "35972",
          "lastname": "",
          "forename": ""
        }
      ],
      "bhl_pages": [
        12114014,
        12114015,
        12114016,
        12114017,
        12114018,
        12114019,
        12114020,
        12114021,
        12114022,
        12114023
      ]
    },
    {
      "reference_id": "50851",
      "genre": "article",
      "title": "XVII. The Larva of Eriocephala allionella. By Thomas Algernon Chapman, M.D., F.E.S",
      "secondary_title": "Transactions of The Royal Entomological Society of London",
      "volume": "46",
      "spage": "391",
      "epage": "392",
      "year": "1898",
      "date": "1898-00-00",
      "issn": "0035-8894",
      "doi": "10.1111\/j.1365-2311.1898.tb03295.x",
      "PageID": "12114024",
      "created": "2010-06-23 17:12:07",
      "updated": "2012-05-25 09:14:10",
      "TitlePageID": "0",
      "authors": [
        {
          "id": "35972",
          "lastname": "",
          "forename": ""
        }
      ],
      "bhl_pages": [
        12114024,
        12114025
      ]
    },
    {
      "reference_id": "50852",
      "genre": "article",
      "title": "XVIII. A list of the Clavicorn Coleoptera of St. Vincent Grenada, and the Grenadines. By G. C: Champion, F.Z.S",
      "secondary_title": "Transactions of The Royal Entomological Society of London",
      "volume": "46",
      "spage": "393",
      "epage": "412",
      "year": "1898",
      "date": "1898-00-00",
      "issn": "0035-8894",
      "doi": "10.1111\/j.1365-2311.1898.tb03296.x",
      "PageID": "12114026",
      "created": "2010-06-23 17:12:11",
      "updated": "2012-05-25 09:14:10",
      "TitlePageID": "0",
      "authors": [
        {
          "id": "35972",
          "lastname": "",
          "forename": ""
        }
      ],
      "bhl_pages": [
        12114026,
        12114027,
        12114028,
        12114029,
        12114030,
        12114031,
        12114032,
        12114033,
        12114034,
        12114035,
        12114036,
        12114037,
        12114038,
        12114039,
        12114040,
        12114041,
        12114042,
        12114043,
        12114044,
        12114045
      ]
    },
    {
      "reference_id": "50853",
      "genre": "article",
      "title": "XIX. Notes on some Syrphidie collected near Aden by Colonel J. W. Yerbury in February and March, 1895. By George Heney Vesrall, F.E.S",
      "secondary_title": "Transactions of The Royal Entomological Society of London",
      "volume": "46",
      "spage": "413",
      "epage": "422",
      "year": "1898",
      "date": "1898-00-00",
      "issn": "0035-8894",
      "doi": "10.1111\/j.1365-2311.1898.tb03297.x",
      "PageID": "12114046",
      "created": "2010-06-23 17:12:14",
      "updated": "2012-05-25 09:14:10",
      "TitlePageID": "0",
      "authors": [
        {
          "id": "35972",
          "lastname": "",
          "forename": ""
        }
      ],
      "bhl_pages": [
        12114046,
        12114047,
        12114048,
        12114049,
        12114050,
        12114051,
        12114052,
        12114053,
        12114054,
        12114055
      ]
    },
    {
      "reference_id": "50854",
      "genre": "article",
      "title": "XX. On some Oriental Scolytid\u0153 of economic importance, with Descriptions of five new Species. By Walter F. H. Blandfobd, M.A., F.Z.S",
      "secondary_title": "Transactions of The Royal Entomological Society of London",
      "volume": "46",
      "spage": "423",
      "epage": "430",
      "year": "1898",
      "date": "1898-00-00",
      "issn": "0035-8894",
      "doi": "10.1111\/j.1365-2311.1898.tb03298.x",
      "PageID": "12114056",
      "created": "2010-06-23 17:12:16",
      "updated": "2012-05-25 09:14:10",
      "TitlePageID": "0",
      "authors": [
        {
          "id": "35972",
          "lastname": "",
          "forename": ""
        }
      ],
      "bhl_pages": [
        12114056,
        12114057,
        12114058,
        12114059,
        12114060,
        12114061,
        12114062,
        12114063
      ]
    },
    {
      "reference_id": "50855",
      "genre": "article",
      "title": "XXI. On some new species of African Pierin\u00e6 in the collection of the British Museum, with notes on seasonal forms of Belenois. By Arthur G. Butler, Ph.D., F.L.S, &c",
      "secondary_title": "Transactions of The Royal Entomological Society of London",
      "volume": "46",
      "spage": "431",
      "epage": "438",
      "year": "1898",
      "date": "1898-00-00",
      "issn": "0035-8894",
      "doi": "10.1111\/j.1365-2311.1898.tb03299.x",
      "PageID": "12114064",
      "created": "2010-06-23 17:12:19",
      "updated": "2012-05-25 09:14:10",
      "TitlePageID": "0",
      "authors": [
        {
          "id": "35972",
          "lastname": "",
          "forename": ""
        }
      ],
      "bhl_pages": [
        12114064,
        12114065,
        12114066,
        12114067,
        12114068,
        12114069,
        12114070,
        12114071
      ]
    },
    {
      "reference_id": "50856",
      "genre": "article",
      "title": "XXII. Considerations on the Genus Tetracanthagyna Selys. By Robert McLachlan, F.R.S., &c",
      "secondary_title": "Transactions of The Royal Entomological Society of London",
      "volume": "46",
      "spage": "439",
      "epage": "444",
      "year": "1898",
      "date": "1898-00-00",
      "issn": "0035-8894",
      "doi": "10.1111\/j.1365-2311.1898.tb03300.x",
      "PageID": "12114072",
      "created": "2010-06-23 17:12:20",
      "updated": "2012-05-25 09:14:10",
      "TitlePageID": "0",
      "authors": [
        {
          "id": "35972",
          "lastname": "",
          "forename": ""
        }
      ],
      "bhl_pages": [
        12114072,
        12114073,
        12114074,
        12114075,
        12114076,
        12114077
      ]
    }
  ]
}