{
  "ItemID": "94130",
  "FullTitle": "Nachrichtenblatt der Bayerischen Entomologen.",
  "VolumeInfo": "v. 1-3 1952-54",
  "articles": [
    {
      "reference_id": "98671",
      "genre": "article",
      "title": "Talaeporia tubulosa bavaralta ssp. n., eine neue Unterart aus den Berchtesgadner Alpen (Lepidoptera, Psychidae)",
      "secondary_title": "Nachrichtenblatt Der Bayerischen Entomologen",
      "volume": "2",
      "spage": "52",
      "epage": "55",
      "year": "1953",
      "date": "1953-00-00",
      "issn": "0027-7452",
      "PageID": "29753970",
      "created": "2011-12-02 12:56:28",
      "updated": "2011-12-02 12:56:28",
      "TitlePageID": "0",
      "authors": [
        
      ],
      "bhl_pages": [
        29753970,
        29753971,
        29753972,
        29753973
      ]
    },
    {
      "reference_id": "98668",
      "genre": "article",
      "title": "Eine neue Agrionide aus Bayern (Odonata)",
      "secondary_title": "Nachrichtenblatt Der Bayerischen Entomologen",
      "volume": "3",
      "spage": "97",
      "epage": "99",
      "year": "1954",
      "date": "1954-00-00",
      "issn": "0027-7452",
      "PageID": "29754117",
      "created": "2011-12-02 12:56:10",
      "updated": "2011-12-02 12:56:10",
      "TitlePageID": "0",
      "authors": [
        
      ],
      "bhl_pages": [
        29754117,
        29754118,
        29754119
      ]
    },
    {
      "reference_id": "98669",
      "genre": "article",
      "title": "Eine neue Bythinus-Art (Col. Pselaphidae) aus dei Nordkette der Karnischen Alpen in Karnten mit einem Tabellenausschnitt der nachstverwandten Arten und zwei Abbildungen",
      "secondary_title": "Nachrichtenblatt Der Bayerischen Entomologen",
      "volume": "3",
      "spage": "100",
      "epage": "102",
      "year": "1954",
      "date": "1954-00-00",
      "issn": "0027-7452",
      "PageID": "29754120",
      "created": "2011-12-02 12:56:16",
      "updated": "2011-12-02 12:56:16",
      "TitlePageID": "0",
      "authors": [
        
      ],
      "bhl_pages": [
        29754120,
        29754121,
        29754122
      ]
    }
  ]
}